aiostream/__init__.py
aiostream/aiter_utils.py
aiostream/core.py
aiostream/manager.py
aiostream/pipe.py
aiostream/py.typed
aiostream/test_utils.py
aiostream/stream/__init__.py
aiostream/stream/advanced.py
aiostream/stream/aggregate.py
aiostream/stream/combine.py
aiostream/stream/create.py
aiostream/stream/misc.py
aiostream/stream/select.py
aiostream/stream/time.py
aiostream/stream/transform.py
aiostream-0.6.4.dist-info/LICENSE
aiostream-0.6.4.dist-info/METADATA
aiostream-0.6.4.dist-info/WHEEL
aiostream-0.6.4.dist-info/top_level.txt
aiostream-0.6.4.dist-info/RECORD
